odoo/addons/sale_product_category_menu/README.rst
odoo/addons/sale_product_category_menu/__init__.py
odoo/addons/sale_product_category_menu/__manifest__.py
odoo/addons/sale_product_category_menu/i18n/pt.po
odoo/addons/sale_product_category_menu/i18n/sale_product_category_menu.pot
odoo/addons/sale_product_category_menu/readme/CONTRIBUTORS.rst
odoo/addons/sale_product_category_menu/readme/DESCRIPTION.rst
odoo/addons/sale_product_category_menu/static/description/icon.png
odoo/addons/sale_product_category_menu/static/description/index.html
odoo/addons/sale_product_category_menu/views/sale_views.xml
odoo12_addon_sale_product_category_menu-12.0.1.0.4.dist-info/METADATA
odoo12_addon_sale_product_category_menu-12.0.1.0.4.dist-info/WHEEL
odoo12_addon_sale_product_category_menu-12.0.1.0.4.dist-info/top_level.txt
odoo12_addon_sale_product_category_menu-12.0.1.0.4.dist-info/RECORD
